setup.cfg
setup.py
assentio/__init__.py
assentio/main.py
assentio/manage.py
assentio/utils.py
assentio.egg-info/PKG-INFO
assentio.egg-info/SOURCES.txt
assentio.egg-info/dependency_links.txt
assentio.egg-info/entry_points.txt
assentio.egg-info/not-zip-safe
assentio.egg-info/requires.txt
assentio.egg-info/top_level.txt
assentio/apps/__init__.py
assentio/apps/admin/__init__.py
assentio/apps/admin/admin.py
assentio/apps/admin/views.py
assentio/apps/admin/widgets.py
assentio/apps/blog/__init__.py
assentio/apps/blog/base.py
assentio/apps/blog/blog.py
assentio/apps/blog/models.py
assentio/apps/blog/portlets.py
assentio/apps/blog/slots.py
assentio/apps/login/__init__.py
assentio/apps/login/login.py
assentio/apps/login/models.py
assentio/apps/login/views.py
assentio/middlewares/__init__.py
assentio/middlewares/caching.py
assentio/tests/__init__.py
assentio/tests/base.py
assentio/tests/test_app.py
assentio/tests/test_blog.py
assentio/tests/test_fts_common.py
assentio/tests/test_user.py