Metadata-Version: 1.0
Name: assentio
Version: 0.1
Summary: A minimal, lightweight flask-based blog
Home-page: https://github.com/kalymero/assentio
Author: Antonio Sagliocco
Author-email: asagliocco@gmail.com
License: WTFPL
Platform: UNKNOWN
Classifier: Programming Language :: Python
